faya/__init__.py
faya/lib/__common.py
faya/lib/__init__.py
faya/lib/__jp_dict.py
faya/lib/__muti.py
faya/lib/__nikkei.py
faya/lib/__pixiv.py
faya/lib/__wiki.py
faya/lib/common.py
faya/lib/jp_dict.py
faya/lib/muti.py
faya/lib/nikkei_top.py
faya/lib/pixiv_daily.py
faya-4.1.3.dist-info/DESCRIPTION.rst
faya-4.1.3.dist-info/METADATA
faya-4.1.3.dist-info/RECORD
faya-4.1.3.dist-info/WHEEL
faya-4.1.3.dist-info/entry_points.txt
faya-4.1.3.dist-info/metadata.json
faya-4.1.3.dist-info/top_level.txt
