Metadata-Version: 2.0
Name: faya
Version: 4.1.3
Summary: personal robot
Home-page: https://github.com/minatsuki-yui/faya
Author: Yue Minatsuki
Author-email: yue.official.jp@gmail.com
License: MIT Licence
Platform: UNKNOWN
Classifier: Development Status :: 4 - Beta
Classifier: Intended Audience :: Developers
Classifier: Programming Language :: Python :: 3.6
Requires-Python: >=3.6
Requires-Dist: click
Requires-Dist: requests
